{
    "name": "Inspection",
    "fields": [
        {
            "fieldName": "date",
            "fieldType": "Instant",
            "fieldValidateRules": [
                "required"
            ]
        },
        {
            "fieldName": "signature",
            "fieldType": "byte[]",
            "fieldTypeBlobContent": "image"
        }
    ],
    "relationships": [
        {
            "relationshipType": "one-to-one",
            "otherEntityName": "location",
            "otherEntityRelationshipName": "inspection",
            "relationshipName": "location",
            "otherEntityField": "address",
            "ownerSide": true
        }
    ],
    "changelogDate": "20190926192508",
    "entityTableName": "inspection",
    "dto": "no",
    "pagination": "no",
    "service": "no",
    "jpaMetamodelFiltering": false,
    "fluentMethods": true,
    "clientRootFolder": "",
    "applications": "*"
}